cosa/__init__.py
cosa/configs/arch/simba.yaml
cosa/configs/mapspace/mapspace.yaml
cosa/configs/workloads/alexnet_graph/_outputs_210.yaml
cosa/configs/workloads/alexnet_graph/_outputs_218.yaml
cosa/configs/workloads/alexnet_graph/_outputs_223.yaml
cosa/configs/workloads/alexnet_graph/_outputs_input.10.yaml
cosa/configs/workloads/alexnet_graph/_outputs_input.2.yaml
cosa/configs/workloads/alexnet_graph/_outputs_input.4.yaml
cosa/configs/workloads/alexnet_graph/_outputs_input.6.yaml
cosa/configs/workloads/alexnet_graph/_outputs_input.8.yaml
cosa/configs/workloads/alexnet_graph/graph.pkl
cosa/configs/workloads/alexnet_graph/layers.yaml
cosa/configs/workloads/alexnet_graph/unique_layers.yaml
cosa/configs/workloads/alexnet_pad_graph/_outputs_input.2.yaml
cosa/configs/workloads/alexnet_pad_graph/unique_layers.yaml
cosa/configs/workloads/deepbench_graph/01_DeepSpeech.yaml
cosa/configs/workloads/deepbench_graph/02_DeepSpeech.yaml
cosa/configs/workloads/deepbench_graph/03_DeepSpeech.yaml
cosa/configs/workloads/deepbench_graph/04_DeepSpeech.yaml
cosa/configs/workloads/deepbench_graph/05_DeepSpeech.yaml
cosa/configs/workloads/deepbench_graph/06_DeepSpeech.yaml
cosa/configs/workloads/deepbench_graph/07_OCR.yaml
cosa/configs/workloads/deepbench_graph/08_OCR.yaml
cosa/configs/workloads/deepbench_graph/09_OCR.yaml
cosa/configs/workloads/deepbench_graph/10_OCR.yaml
cosa/configs/workloads/deepbench_graph/11_Face_Recognition.yaml
cosa/configs/workloads/deepbench_graph/12_Face_Recognition.yaml
cosa/configs/workloads/deepbench_graph/13_Face_Recognition.yaml
cosa/configs/workloads/deepbench_graph/14_Face_Recognition.yaml
cosa/configs/workloads/deepbench_graph/15_Face_Recognition.yaml
cosa/configs/workloads/deepbench_graph/16_Vision.yaml
cosa/configs/workloads/deepbench_graph/17_Vision.yaml
cosa/configs/workloads/deepbench_graph/18_Vision.yaml
cosa/configs/workloads/deepbench_graph/19_Vision.yaml
cosa/configs/workloads/deepbench_graph/20_Vision.yaml
cosa_scheduler-0.1.0.dist-info/entry_points.txt
cosa_scheduler-0.1.0.dist-info/LICENSE
cosa_scheduler-0.1.0.dist-info/WHEEL
cosa_scheduler-0.1.0.dist-info/METADATA
cosa_scheduler-0.1.0.dist-info/RECORD
