Metadata-Version: 2.1
Name: cosa-scheduler
Version: 0.1.0
Summary: A constrained-optimization based scheduler for spatial DNN accelerators
License: BSD-2-Clause
Author: Qijing Huang
Author-email: qijing.huang@berkeley.edu
Requires-Python: >=3.8,<4.0
Classifier: License :: OSI Approved :: BSD License
Classifier: Programming Language :: Python :: 3
Classifier: Programming Language :: Python :: 3.8
Classifier: Programming Language :: Python :: 3.9
Classifier: Programming Language :: Python :: 3.10
Requires-Dist: PyYAML (>=6.0,<7.0)
Requires-Dist: gurobipy (>=9.5.1,<10.0.0)
Requires-Dist: numpy (>=1.22.3,<2.0.0)
